msgu/__init__.py
msgu/cardio/__init__.py
msgu/cardio/ecg.py
msgu/gauss/__init__.py
msgu/gauss/gaussians.py
msgu/mixture/__init__.py
msgu/mixture/prsynth.py
msgu/noise/__init__.py
msgu/noise/noise.py
msgu/periodic/__init__.py
msgu/periodic/tidal.py
msgu/trajectory/__init__.py
msgu/trajectory/scurves.py
magnes_signal_generation_utility-0.1.0.dist-info/METADATA
magnes_signal_generation_utility-0.1.0.dist-info/WHEEL
magnes_signal_generation_utility-0.1.0.dist-info/licenses/LICENSE
magnes_signal_generation_utility-0.1.0.dist-info/RECORD
