Metadata-Version: 2.4
Name: magnes-signal-generation-utility
Version: 0.1.0
Summary: Utility to generate signals for algorithm development and verification.
Author-email: Alessandro Schaer <aschaer@magnes.ch>, Henrik Maurenbrecher <henrikm@magnes.ch>
License-File: LICENSE
Requires-Python: >=3.12
Requires-Dist: matplotlib>=3.10.6
Requires-Dist: numpy>=2.3.3
Requires-Dist: scipy>=1.16.2
